cozmo/LICENSE.txt
cozmo/__init__.py
cozmo/_clad.py
cozmo/action.py
cozmo/anim.py
cozmo/annotate.py
cozmo/audio.py
cozmo/base.py
cozmo/behavior.py
cozmo/camera.py
cozmo/clad_protocol.py
cozmo/conn.py
cozmo/event.py
cozmo/exceptions.py
cozmo/faces.py
cozmo/lights.py
cozmo/nav_memory_map.py
cozmo/objects.py
cozmo/oled_face.py
cozmo/opengl.py
cozmo/pets.py
cozmo/robot.py
cozmo/robot_alignment.py
cozmo/run.py
cozmo/song.py
cozmo/tkview.py
cozmo/util.py
cozmo/version.py
cozmo/world.py
cozmo/assets/LICENSE.txt
cozmo/assets/cozmo.mtl
cozmo/assets/cozmo.obj
cozmo/assets/cube.obj
cozmo/assets/cube1.jpg
cozmo/assets/cube1.mtl
cozmo/assets/cube2.jpg
cozmo/assets/cube2.mtl
cozmo/assets/cube3.jpg
cozmo/assets/cube3.mtl
cozmo/usbmux/__init__.py
cozmo/usbmux/usbmux.py
cozmo-1.4.9.dist-info/LICENSE.txt
cozmo-1.4.9.dist-info/METADATA
cozmo-1.4.9.dist-info/WHEEL
cozmo-1.4.9.dist-info/top_level.txt
cozmo-1.4.9.dist-info/zip-safe
cozmo-1.4.9.dist-info/RECORD
