Metadata-Version: 2.1
Name: cozmo
Version: 1.4.9
Summary: SDK for Anki Cozmo, the small robot with the big personality
Home-page: https://developer.anki.com
Author: Anki, Inc
Author-email: developer@anki.com
License: Apache License, Version 2.0
Keywords: anki,cozmo,robot,robotics,sdk
Platform: UNKNOWN
Classifier: Development Status :: 5 - Production/Stable
Classifier: Intended Audience :: Developers
Classifier: Topic :: Software Development :: Libraries
Classifier: License :: OSI Approved :: Apache Software License
Classifier: Programming Language :: Python :: 3.5
Requires-Dist: cozmoclad (==3.3.0)
Provides-Extra: 3dviewer
Requires-Dist: PyOpenGL (>=3.1) ; extra == '3dviewer'
Requires-Dist: Pillow (>=3.3) ; extra == '3dviewer'
Requires-Dist: numpy (>=1.11) ; extra == '3dviewer'
Provides-Extra: camera
Requires-Dist: Pillow (>=3.3) ; extra == 'camera'
Requires-Dist: numpy (>=1.11) ; extra == 'camera'
Provides-Extra: test
Requires-Dist: tox ; extra == 'test'
Requires-Dist: pytest ; extra == 'test'
